sheepcord/__init__.py
sheepcord-0.1.0.dist-info/WHEEL
sheepcord-0.1.0.dist-info/METADATA
sheepcord-0.1.0.dist-info/RECORD
